cxbuilder_aws_lex/__init__.py
cxbuilder_aws_lex/py.typed
cxbuilder_aws_lex/_jsii/__init__.py
cxbuilder_aws_lex/_jsii/aws-lex@1.3.0.jsii.tgz
cxbuilder_aws_lex-1.3.0.dist-info/LICENSE
cxbuilder_aws_lex-1.3.0.dist-info/METADATA
cxbuilder_aws_lex-1.3.0.dist-info/WHEEL
cxbuilder_aws_lex-1.3.0.dist-info/top_level.txt
cxbuilder_aws_lex-1.3.0.dist-info/RECORD
