Metadata-Version: 2.1
Name: cxbuilder-aws-lex
Version: 1.3.0
Summary: Higher-level (L2) constructs for AWS LexV2 bot creation using the AWS CDK
Home-page: https://github.com/cxbuilder/aws-lex#readme
Author: CXBuilder<ivan@cxbuilder.ai>
License: MIT
Project-URL: Source, https://github.com/cxbuilder/aws-lex.git
Classifier: Intended Audience :: Developers
Classifier: Operating System :: OS Independent
Classifier: Programming Language :: JavaScript
Classifier: Programming Language :: Python :: 3 :: Only
Classifier: Programming Language :: Python :: 3.9
Classifier: Programming Language :: Python :: 3.10
Classifier: Programming Language :: Python :: 3.11
Classifier: Typing :: Typed
Classifier: Development Status :: 5 - Production/Stable
Classifier: License :: OSI Approved
Classifier: Framework :: AWS CDK
Classifier: Framework :: AWS CDK :: 2
Requires-Python: ~=3.9
License-File: LICENSE
Requires-Dist: aws-cdk-lib ==2.194.0
Requires-Dist: cdk-nag <3.0.0,>=2.37.9
Requires-Dist: constructs <11.0.0,>=10.0.5
Requires-Dist: jsii <2.0.0,>=1.114.1
Requires-Dist: publication >=0.0.3
Requires-Dist: typeguard <4.3.0,>=2.13.3
